setup.py
Products/__init__.py
Products.TrustedExecutables.egg-info/PKG-INFO
Products.TrustedExecutables.egg-info/SOURCES.txt
Products.TrustedExecutables.egg-info/dependency_links.txt
Products.TrustedExecutables.egg-info/namespace_packages.txt
Products.TrustedExecutables.egg-info/not-zip-safe
Products.TrustedExecutables.egg-info/requires.txt
Products.TrustedExecutables.egg-info/top_level.txt
Products/TrustedExecutables/LICENSE.txt
Products/TrustedExecutables/PythonExpr.py
Products/TrustedExecutables/README.txt
Products/TrustedExecutables/TrustedExpression.py
Products/TrustedExecutables/TrustedFSPageTemplate.py
Products/TrustedExecutables/TrustedFSPythonScript.py
Products/TrustedExecutables/TrustedPageTemplateFile.py
Products/TrustedExecutables/TrustedPythonScript.py
Products/TrustedExecutables/TrustedPythonScriptMixin.py
Products/TrustedExecutables/Utils.py
Products/TrustedExecutables/VERSION.txt
Products/TrustedExecutables/__init__.py
Products/TrustedExecutables/pymixin_2.py
Products/TrustedExecutables/pymixin_4.py
Products/TrustedExecutables/tests/TestBase.py
Products/TrustedExecutables/tests/__init__.py
Products/TrustedExecutables/tests/configure.zcml
Products/TrustedExecutables/tests/testTrustedFSObjects.py
Products/TrustedExecutables/tests/testTrustedPageTemplateFile.py
Products/TrustedExecutables/tests/Files/pt.xpt
Products/TrustedExecutables/tests/Files/pt_call_py.xpt
Products/TrustedExecutables/tests/Files/py.xpy