Metadata-Version: 1.1
Name: Products.TrustedExecutables
Version: 2.0
Summary: Trusted Zope 2 executables (scripts, templates) -- unrestricted by Zope 2 security. For Zope 2.13 and above
Home-page: http://www.dieter.handshake.de/pyprojects/zope
Author: Dieter Maurer
Author-email: dieter@handshake.de
License: BSD (see "Products/TrustedExecutables/LICENSE.txt", for details)
Keywords: Zope 2,trusted,executables,unrestricted,security
Platform: UNKNOWN
Classifier: Development Status :: 5 - Production/Stable
Classifier: Intended Audience :: Developers
Classifier: License :: OSI Approved :: BSD License
Classifier: Framework :: Zope2
Classifier: Framework :: Zope
Classifier: Framework :: Zope :: 4
Classifier: Operating System :: OS Independent
Classifier: Programming Language :: Python
Classifier: Programming Language :: Python :: 2.7
Classifier: Programming Language :: Python :: 3
Classifier: Topic :: Utilities
